k1usnsst/__init__.py
k1usnsst/__main__.py
k1usnsst/data/JetBrainsMono-Regular.ttf
k1usnsst/data/cwmacros_sst.txt
k1usnsst/data/dialog.ui
k1usnsst/data/k6gte-k1usnsst.desktop
k1usnsst/data/k6gte-k1usnsst.png
k1usnsst/data/main.ui
k1usnsst/data/settings.ui
k1usnsst/icon/gear16x16.png
k1usnsst/icon/radio_green.png
k1usnsst/icon/radio_grey.png
k1usnsst/icon/radio_red.png
k1usnsst/lib/__init__.py
k1usnsst/lib/cwinterface.py
k1usnsst/lib/lookup.py
k1usnsst/lib/settings.py
k1usnsst-24.5.13.dist-info/LICENSE
k1usnsst-24.5.13.dist-info/METADATA
k1usnsst-24.5.13.dist-info/WHEEL
k1usnsst-24.5.13.dist-info/entry_points.txt
k1usnsst-24.5.13.dist-info/top_level.txt
k1usnsst-24.5.13.dist-info/RECORD
